CHANGELOG.md
LICENSE.md
MANIFEST.in
README.md
requirements.txt
setup.py
baidupcsapi/__init__.py
baidupcsapi/api.py
baidupcsapi.egg-info/PKG-INFO
baidupcsapi.egg-info/SOURCES.txt
baidupcsapi.egg-info/dependency_links.txt
baidupcsapi.egg-info/not-zip-safe
baidupcsapi.egg-info/requires.txt
baidupcsapi.egg-info/top_level.txt