Metadata-Version: 1.1
Name: baidupcsapi
Version: 0.9.4
Summary: 百度网盘API
Home-page: https://github.com/ly0/baidupcsapi
Author: ly0, mozillazg101
Author-email: latyas@gmail.com,mozillazg101@gmail.com
License: MIT
Download-URL: https://github.com/ly0/baidupcsapi
Keywords: 百度网盘,百度云,API
Platform: UNKNOWN
Classifier: Development Status :: 5 - Production/Stable
Classifier: Intended Audience :: Developers
Classifier: License :: OSI Approved :: MIT License
Classifier: Operating System :: OS Independent
Classifier: Programming Language :: Python
Classifier: Programming Language :: Python :: 3
Classifier: Topic :: Utilities
